Workbook

Sheet Task-1(Data-Quality-Audit)
A1: Data Quality Assessment
A3: Total Orders | B3: =COUNTA(Orders!A2:A251) -> 250 | C3: Duplicate Oders | D3: 70 | E3: Inconsistent Date Formats | F3: 5
A4: Blank Values | C4: Country Variations | E4: Negative Quantity Orders | F4: 12
A5: Customer Name | B5: =COUNTBLANK(Orders!D2:D2036) -> 15 | C5: United States | D5: 4 | E5: Test Orders | F5: None
A6: Customer Email | B6: =COUNTBLANK(Orders!F2:F2036) -> 121 | C6: United Kindom | D6: 4 | E6: Currency as Text | F6: None
A7: Product Name | B7: =COUNTBLANK(Orders!G2:G2036) -> 0 | C7: Germany | D7: 2
A8: Category | B8: =COUNTBLANK(Orders!H2:H2036) -> 0 | C8: Australia | D8: 2
A9: SKU | B9: =COUNTBLANK(Orders!I2:I2036) -> 0 | C9: Canada | D9: 2
A10: Quantity | B10: =COUNTBLANK(Orders!J2:J2036) -> 0 | C10: Pakistan | D10: 2
A11: Unit Price | B11: =COUNTBLANK(Orders!K2:K2036) -> 0
A12: Discount Code | B12: =COUNTBLANK(Orders!L2:L2036) -> 910
A13: Discount Amount | B13: =COUNTBLANK(Orders!M2:M2036) -> 0
A14: Shipping | B14: =COUNTBLANK(Orders!N2:N2036) -> 0
A15: Total | B15: =COUNTBLANK(Orders!O2:O2036) -> 0
A16: Payment Method | B16: =COUNTBLANK(Orders!P2:P2036) -> 0
A17: Channel | B17: =COUNTBLANK(Orders!Q2:Q2036) -> 0
A18: Order status | B18: =COUNTBLANK(Orders!R2:R2036) -> 0
A19: Country | B19: =COUNTBLANK(Orders!#REF!) -> #REF!
A20: State | B20: =COUNTBLANK(Orders!T2:T2036) -> 1054
A21: City | B21: =COUNTBLANK(Orders!V2:V2036) -> 0

Sheet Cleaning Tasks
A2: Sales by Country | D2: Missing States Probem | G2: Missing Customer Emails
A3: Row Labels | B3: Sum of Sales | D3: Status | E3: Count
A4: Australia | B4: 1844.37 | D4: Valid | E4: =COUNTIF(Orders!U:U,D4) -> 981 | G4: Total Orders | H4: =COUNTA(Orders!A2:A2036) -> 2035
A5: Canada | B5: 1595.49 | D5: Missing | E5: =COUNTIF(Orders!U:U,D5) -> 0 | G5: Missing Emails | H5: =COUNTBLANK(Orders!F2:F2036) -> 121
A6: Germany | B6: 1191.28 | D6: Not Required | E6: =COUNTIF(Orders!U:U,D6) -> 1054 | G6: Missing Email % | H6: =COUNTBLANK(Orders!F2:F2036)/COUNTA(Orders!A2:A2036) -> 0.059459459
A7: Pakistan | B7: 1167.83 | G7: Emails status by differet channels
A8: United Kingdom | B8: 1311.68 | G8: Count of Order ID | H8: Column Labels
A9: United States | B9: 6345.76 | G9: Row Labels | H9: Email Available | I9: Missing Email | J9: Grand Total
A10: Grand Total | B10: 13456.41 | G10: Online Store | H10: 928 | I10: 65 | J10: 993
G11: Facebook | H11: 332 | I11: 24 | J11: 356
G12: POS | H12: 309 | I12: 20 | J12: 329
G13: Instagram | H13: 345 | I13: 12 | J13: 357
G14: Grand Total | H14: 1914 | I14: 121 | J14: 2035

Sheet Orders
A1: Order ID | B1: Formatted Order Date | C1: Order Date | D1: Customer Name | E1: Email Status | F1: Customer Email | G1: Product Name | H1: Category | I1: SKU | J1: Quantity | K1: Unit Price | L1: Discount Code | M1: Discount Amount | N1: Shipping | O1: Total | P1: Payment Method | Q1: Channel | R1: Order Status | S1: Country | T1: State | U1: State Status | V1: City
A2: #1042 | B2: =IF(ISNUMBER(C2),C2,DATEVALUE(SUBSTITUTE(TRIM(C2),CHAR(160)," "))) -> 46238.58 | C2: 46238.58 | D2: Angie Martin | E2: =IF(TRIM(F2)="","Missing Email","Email Available") -> Email Available | F2: angie.martin506@icloud.com | G2: Running Shoes - Women's | H2: Footwear | I2: FTW-RUN-W | J2: -1 | K2: 54.99 | L2: VIP15 | M2: 8.25 | N2: 5.99 | O2: 52.73 | P2: PayPal | Q2: Online Store | R2: fulfilled | S2: Pakistan | U2: =IF(AND(S2="United States",T2=""),"Missing state",IF(T2="","Not Required","Valid")) -> Not Required | V2: West Travis
A3: #1083 | B3: =IF(ISNUMBER(C3),C3,DATEVALUE(SUBSTITUTE(TRIM(C3),CHAR(160)," "))) -> 46238.58 | C3: 46238.58 | D3: Johnathan Sloan | E3: =IF(TRIM(F3)="","Missing Email","Email Available") -> Email Available | F3: johnathan.sloan721@outlook.com | G3: Running Shoes - Men's | H3: Footwear | I3: FTW-RUN-M | J3: -1 | K3: 54.99 | L3: SAVE20 | M3: $11.00 | N3: 5.99 | O3: 49.98 | P3: Apple Pay | Q3: Online Store | R3: fulfilled | S3: Pakistan | U3: =IF(AND(S3="United States",T3=""),"Missing state",IF(T3="","Not Required","Valid")) -> Not Required | V3: Robertborough
A4: #1371 | B4: =IF(ISNUMBER(C4),C4,DATEVALUE(SUBSTITUTE(TRIM(C4),CHAR(160)," "))) -> 46238.583 | C4: 46238.583 | D4: Andrew Vargas | E4: =IF(TRIM(F4)="","Missing Email","Email Available") -> Email Available | F4: andrew.vargas381@outlook.com | G4: Hooded Sweatshirt | H4: Apparel | I4: APR-HOD-GRY | J4: -1 | K4: 34.99 | M4: 0 | N4: 4.99 | O4: 39.98 | P4: PayPal | Q4: Online Store | R4: cancelled | S4: Canada | U4: =IF(AND(S4="United States",T4=""),"Missing state",IF(T4="","Not Required","Valid")) -> Not Required | V4: Port Jasmineview
A5: #1463 | B5: =IF(ISNUMBER(C5),C5,DATEVALUE(SUBSTITUTE(TRIM(C5),CHAR(160)," "))) -> 46238.581 | C5: 46238.581 | D5: Conway, Brittney | E5: =IF(TRIM(F5)="","Missing Email","Email Available") -> Email Available | F5: brittney.conway383@outlook.com | G5: Yoga Mat - Extra Thick | H5: Sports & Outdoors | I5: SP-YGM-EX | J5: -2 | K5: 22.99 | M5: $0.00 | N5: 7.99 | O5: 53.97 | P5: Apple Pay | Q5: Online Store | R5: fulfilled | S5: United States | T5: Texas | U5: =IF(AND(S5="United States",T5=""),"Missing state",IF(T5="","Not Required","Valid")) -> Valid | V5: North Nathan
A6: #1472 | B6: =IF(ISNUMBER(C6),C6,DATEVALUE(SUBSTITUTE(TRIM(C6),CHAR(160)," "))) -> 46120 | C6: 08/04/2026 | D6: Christy Phillips | E6: =IF(TRIM(F6)="","Missing Email","Email Available") -> Email Available | F6: christy.phillips291@gmail.com | G6: Hooded Sweatshirt | H6: Apparel | I6: APR-HOD-GRY | J6: -1 | K6: 34.99 | L6: VIP15 | M6: 5.25 | N6: 7.99 | O6: 37.73 | P6: Apple Pay | Q6: POS | R6: cancelled | S6: Pakistan | U6: =IF(AND(S6="United States",T6=""),"Missing state",IF(T6="","Not Required","Valid")) -> Not Required | V6: New Claire
A7: #1632 | B7: =IF(ISNUMBER(C7),C7,DATEVALUE(SUBSTITUTE(TRIM(C7),CHAR(160)," "))) -> 46120 | C7: 46120 | D7: Kenneth Morgan | E7: =IF(TRIM(F7)="","Missing Email","Email Available") -> Email Available | F7: kenneth.morgan181@outlook.com | G7: Backpack - 25L | H7: Accessories | I7: ACC-BPK-25L | J7: -3 | K7: 32.99 | L7: WELCOME10 | M7: 9.9 | N7: 0 | O7: 89.07 | P7: Apple Pay | Q7: Online Store | R7: fulfilled | S7: United States | T7: Arizona | U7: =IF(AND(S7="United States",T7=""),"Missing state",IF(T7="","Not Required","Valid")) -> Valid | V7: West David
A8: #1836 | B8: =IF(ISNUMBER(C8),C8,DATEVALUE(SUBSTITUTE(TRIM(C8),CHAR(160)," "))) -> 46238.586 | C8: 46238.586 | D8: Sergio Turner | E8: =IF(TRIM(F8)="","Missing Email","Email Available") -> Email Available | F8: sergio.turner744@outlook.com | G8: Wireless Mouse | H8: Electronics | I8: ELC-MSE-WL | J8: -2 | K8: 11.99 | M8: 0 | N8: 4.99 | O8: 28.97 | P8: Credit Card | Q8: Facebook | R8: fulfilled | S8: Germany | U8: =IF(AND(S8="United States",T8=""),"Missing state",IF(T8="","Not Required","Valid")) -> Not Required | V8: Fordburgh
A9: #2008 | B9: =IF(ISNUMBER(C9),C9,DATEVALUE(SUBSTITUTE(TRIM(C9),CHAR(160)," "))) -> 46238.589 | C9: 46238.589 | D9: Jacob Gibbs | E9: =IF(TRIM(F9)="","Missing Email","Email Available") -> Email Available | F9: jacob.gibbs527@gmail.com | G9: Classic Cotton T-Shirt | H9: Apparel | I9: TSH-BLK-M | J9: -2 | K9: 14.99 | M9: 0 | N9: 4.99 | O9: 34.97 | P9: Shopify Payments | Q9: Online Store | R9: fulfilled | S9: United States | T9: North Carolina | U9: =IF(AND(S9="United States",T9=""),"Missing state",IF(T9="","Not Required","Valid")) -> Valid | V9: Keyburgh
A10: #2485 | B10: =IF(ISNUMBER(C10),C10,DATEVALUE(SUBSTITUTE(TRIM(C10),CHAR(160)," "))) -> 46238.587 | C10: 46238.587 | D10: George Gould | E10: =IF(TRIM(F10)="","Missing Email","Email Available") -> Email Available | F10: george.gould10@yahoo.com | G10: Running Shoes - Women's | H10: Footwear | I10: FTW-RUN-W | J10: -1 | K10: $54.99 | M10: 0 | N10: 7.99 | O10: 62.98 | P10: Google Pay | Q10: Online Store | R10: fulfilled | S10: Canada | U10: =IF(AND(S10="United States",T10=""),"Missing state",IF(T10="","Not Required","Valid")) -> Not Required | V10: Port Jenniferburgh
A11: #2687 | B11: =IF(ISNUMBER(C11),C11,DATEVALUE(SUBSTITUTE(TRIM(C11),CHAR(160)," "))) -> 46238.583 | C11: 46238.583 | D11: Karen Bautista | E11: =IF(TRIM(F11)="","Missing Email","Email Available") -> Email Available | F11: karen.bautista779@icloud.com | G11: Vitamin C Serum 30ml | H11: Beauty | I11: BTY-SRM-30 | J11: -1 | K11: 24.99 | M11: 0 | N11: 5.99 | O11: 30.98 | P11: Apple Pay | Q11: Online Store | R11: fulfilled | S11: United States | T11: Washington | U11: =IF(AND(S11="United States",T11=""),"Missing state",IF(T11="","Not Required","Valid")) -> Valid | V11: Patrickmouth
A12: #2862 | B12: =IF(ISNUMBER(C12),C12,DATEVALUE(SUBSTITUTE(TRIM(C12),CHAR(160)," "))) -> 46238 | C12: 2026-08-04 | D12: Linda Scott | E12: =IF(TRIM(F12)="","Missing Email","Email Available") -> Email Available | F12: linda.scott2@icloud.com | G12: Vitamin C Serum 30ml | H12: Beauty | I12: BTY-SRM-30 | J12: -1 | K12: 24.99 | M12: 0 | N12: 4.99 | O12: 29.98 | P12: Google Pay | Q12: Facebook | R12: fulfilled | S12: Canada | U12: =IF(AND(S12="United States",T12=""),"Missing state",IF(T12="","Not Required","Valid")) -> Not Required | V12: South Lisaton
A13: #2888 | B13: =IF(ISNUMBER(C13),C13,DATEVALUE(SUBSTITUTE(TRIM(C13),CHAR(160)," "))) -> 46238.583 | C13: 46238.583 | D13: Frederick Bean | E13: =IF(TRIM(F13)="","Missing Email","Email Available") -> Email Available | F13: frederick.bean141@outlook.com | G13: Leather Wallet - Brown | H13: Accessories | I13: ACC-WLT-BRN | J13: -2 | K13: 19.99 | M13: 0 | N13: 7.99 | O13: 47.97 | P13: Google Pay | Q13: Online Store | R13: pending | S13: United States | T13: California | U13: =IF(AND(S13="United States",T13=""),"Missing state",IF(T13="","Not Required","Valid")) -> Valid | V13: Barnesville
A14: #1003 | B14: =IF(ISNUMBER(C14),C14,DATEVALUE(SUBSTITUTE(TRIM(C14),CHAR(160)," "))) -> 46238.58 | C14: 46238.58 | D14: THOMAS ROJAS | E14: =IF(TRIM(F14)="","Missing Email","Email Available") -> Email Available | F14: thomas.rojas667@icloud.com | G14: Slim Fit Denim Jeans | H14: Apparel | I14: JNS-BLU-32 | J14: 1 | K14: 39.99 | M14: 0 | N14: 5.99 | O14: 45.98 | P14: Credit Card | Q14: Online Store | R14: fulfilled | S14: United States | T14: North Carolina | U14: =IF(AND(S14="United States",T14=""),"Missing state",IF(T14="","Not Required","Valid")) -> Valid | V14: West Cynthialand
A15: #1027 | B15: =IF(ISNUMBER(C15),C15,DATEVALUE(SUBSTITUTE(TRIM(C15),CHAR(160)," "))) -> 46238.583 | C15: 46238.583 | D15: Sandra Wilson | E15: =IF(TRIM(F15)="","Missing Email","Email Available") -> Email Available | F15: sandra.wilson554@outlook.com | G15: Vitamin C Serum 30ml | H15: Beauty | I15: BTY-SRM-30 | J15: 1 | K15: 24.99 | L15: VIP15 | M15: 3.75 | N15: 7.99 | O15: 29.23 | P15: Apple Pay | Q15: Online Store | R15: pending | S15: Canada | U15: =IF(AND(S15="United States",T15=""),"Missing state",IF(T15="","Not Required","Valid")) -> Not Required | V15: Hollyport
A16: #1172 | B16: =IF(ISNUMBER(C16),C16,DATEVALUE(SUBSTITUTE(TRIM(C16),CHAR(160)," "))) -> 46238.584 | C16: 46238.584 | D16: TINA SINGH | E16: =IF(TRIM(F16)="","Missing Email","Email Available") -> Email Available | F16: tina.singh98@icloud.com | G16: Leather Wallet - Brown | H16: Accessories | I16: ACC-WLT-BRN | J16: 1 | K16: 19.99 | M16: 0 | N16: 5.99 | O16: 25.98 | P16: Credit Card | Q16: Online Store | R16: fulfilled | S16: United States | T16: Washington | U16: =IF(AND(S16="United States",T16=""),"Missing state",IF(T16="","Not Required","Valid")) -> Valid | V16: East Heathertown
A17: #1260 | B17: =IF(ISNUMBER(C17),C17,DATEVALUE(SUBSTITUTE(TRIM(C17),CHAR(160)," "))) -> 46238.586 | C17: 46238.586 | D17: Morgan Brown | E17: =IF(TRIM(F17)="","Missing Email","Email Available") -> Email Available | F17: morgan.brown933@gmail.com | G17: Wireless Bluetooth Earbuds | H17: Electronics | I17: ELC-WBE-01 | J17: 1 | K17: 29.99 | L17: FREESHIP | M17: 0 | N17: 0 | O17: 29.99 | P17: Apple Pay | Q17: Online Store | R17: pending | S17: United States | T17: Florida | U17: =IF(AND(S17="United States",T17=""),"Missing state",IF(T17="","Not Required","Valid")) -> Valid | V17: Austinbury
A18: #1262 | B18: =IF(ISNUMBER(C18),C18,DATEVALUE(SUBSTITUTE(TRIM(C18),CHAR(160)," "))) -> 46238.586 | C18: 46238.586 | D18: Mark Mata | E18: =IF(TRIM(F18)="","Missing Email","Email Available") -> Email Available | F18: mark.mata757@outlook.com | G18: Facial Cleanser 200ml | H18: Beauty | I18: BTY-CLN-200 | J18: 1 | K18: 13.49 | M18: 0 | N18: 7.99 | O18: 21.48 | P18: Apple Pay | Q18: Facebook | R18: pending | S18: United States | T18: Washington | U18: =IF(AND(S18="United States",T18=""),"Missing state",IF(T18="","Not Required","Valid")) -> Valid | V18: Davidburgh
A19: #1305 | B19: =IF(ISNUMBER(C19),C19,DATEVALUE(SUBSTITUTE(TRIM(C19),CHAR(160)," "))) -> 46238.586 | C19: 46238.586 | D19: Amy Maldonado | E19: =IF(TRIM(F19)="","Missing Email","Email Available") -> Email Available | F19: amy.maldonado44@gmail.com | G19: Polarized Sunglasses | H19: Accessories | I19: ACC-SUN-01 | J19: 1 | K19: 16.99 | M19: 0 | N19: 5.99 | O19: 22.98 | P19: PayPal | Q19: Online Store | R19: fulfilled | S19: Pakistan | U19: =IF(AND(S19="United States",T19=""),"Missing state",IF(T19="","Not Required","Valid")) -> Not Required | V19: Matthewstad
A20: #1652 | B20: =IF(ISNUMBER(C20),C20,DATEVALUE(SUBSTITUTE(TRIM(C20),CHAR(160)," "))) -> 46238.585 | C20: 46238.585 | D20: Sean Frank | E20: =IF(TRIM(F20)="","Missing Email","Email Available") -> Email Available | F20: sean.frank587@icloud.com | G20: Kids Building Blocks Set | H20: Toys | I20: TOY-BLK-SET | J20: 2 | K20: 27.99 | L20: WELCOME10 | M20: 5.6 | N20: 7.99 | O20: $58.37 | P20: Credit Card | Q20: Facebook | R20: fulfilled | S20: Australia | U20: =IF(AND(S20="United States",T20=""),"Missing state",IF(T20="","Not Required","Valid")) -> Not Required | V20: Port Josephborough
A21: #1719 | B21: =IF(ISNUMBER(C21),C21,DATEVALUE(SUBSTITUTE(TRIM(C21),CHAR(160)," "))) -> 46238.589 | C21: 46238.589 | D21: GRACE RAY | E21: =IF(TRIM(F21)="","Missing Email","Email Available") -> Email Available | F21: grace.ray807@yahoo.com | G21: Wireless Mouse | H21: Electronics | I21: ELC-MSE-WL | J21: 2 | K21: 11.99 | M21: 0 | N21: 7.99 | O21: 31.97 | P21: Apple Pay | Q21: Facebook | R21: cancelled | S21: United Kingdom | U21: =IF(AND(S21="United States",T21=""),"Missing state",IF(T21="","Not Required","Valid")) -> Not Required | V21: Lutzton
A22: #1781 | B22: =DATE(VALUE(RIGHT(C22,4)),MATCH(LEFT(C22,3),{"Jan","Feb","Mar","Apr","May","Jun","Jul","Aug","Sep","Oct","Nov","Dec"},0),VALUE(MID(C22,5,2))) -> 46238 | C22: Aug 04, 2026 | D22: Sharon Brown | E22: =IF(TRIM(F22)="","Missing Email","Email Available") -> Missing Email | G22: Running Shoes - Men's | H22: Footwear | I22: FTW-RUN-M | J22: 1 | K22: 54.99 | M22: 0 | N22: 4.99 | O22: 59.98 | P22: Shopify Payments | Q22: POS | R22: fulfilled | S22: United States | T22: Arizona | U22: =IF(AND(S22="United States",T22=""),"Missing state",IF(T22="","Not Required","Valid")) -> Valid | V22: Clarkmouth
A23: #1798 | B23: =IF(ISNUMBER(C23),C23,DATEVALUE(SUBSTITUTE(TRIM(C23),CHAR(160)," "))) -> 46238.582 | C23: 46238.582 | D23: Tina Singh | E23: =IF(TRIM(F23)="","Missing Email","Email Available") -> Email Available | F23: tina.singh98@icloud.com | G23: Adjustable Dumbbell Set | H23: Sports & Outdoors | I23: SP-DMB-ADJ | J23: 2 | K23: 89.99 | M23: 0 | N23: 0 | O23: 179.98 | P23: Google Pay | Q23: POS | R23: pending | S23: United States | T23: Georgia | U23: =IF(AND(S23="United States",T23=""),"Missing state",IF(T23="","Not Required","Valid")) -> Valid | V23: North Shannon
A24: #1818 | B24: =IF(ISNUMBER(C24),C24,DATEVALUE(SUBSTITUTE(TRIM(C24),CHAR(160)," "))) -> 46120 | C24: 08/04/2026 | D24: Amanda Harris | E24: =IF(TRIM(F24)="","Missing Email","Email Available") -> Email Available | F24: amanda.harris197@gmail.com | G24: USB-C Fast Charger 20W | H24: Electronics | I24: ELC-CHG-20 | J24: 1 | K24: 15.49 | M24: 0 | N24: 5.99 | O24: 21.48 | P24: Google Pay | Q24: Instagram | R24: pending | S24: United States | T24: Washington | U24: =IF(AND(S24="United States",T24=""),"Missing state",IF(T24="","Not Required","Valid")) -> Valid | V24: Richardsonburgh
A25: #1859 | B25: =IF(ISNUMBER(C25),C25,DATEVALUE(SUBSTITUTE(TRIM(C25),CHAR(160)," "))) -> 46238.58 | C25: 46238.58 | D25: Sarah Webb | E25: =IF(TRIM(F25)="","Missing Email","Email Available") -> Email Available | F25: sarah.webb997@outlook.com | G25: Adjustable Dumbbell Set | H25: Sports & Outdoors | I25: SP-DMB-ADJ | J25: 3 | K25: 89.99 | L25: VIP15 | M25: 40.5 | N25: 0 | O25: 229.47 | P25: PayPal | Q25: Facebook | R25: fulfilled | S25: Germany | U25: =IF(AND(S25="United States",T25=""),"Missing state",IF(T25="","Not Required","Valid")) -> Not Required | V25: North Ronald
A26: #1866 | B26: =IF(ISNUMBER(C26),C26,DATEVALUE(SUBSTITUTE(TRIM(C26),CHAR(160)," "))) -> 46238.579 | C26: 46238.579 | D26: Melissa Jones | E26: =IF(TRIM(F26)="","Missing Email","Email Available") -> Missing Email | G26: Ceramic Coffee Mug Set (4pc) | H26: Home & Kitchen | I26: HK-MUG-4PK | J26: 1 | K26: 18.99 | L26: FREESHIP | M26: 0 | N26: 0 | O26: 18.99 | P26: Credit Card | Q26: Online Store | R26: pending | S26: United States | T26: Florida | U26: =IF(AND(S26="United States",T26=""),"Missing state",IF(T26="","Not Required","Valid")) -> Valid | V26: Kelseybury
A27: #1948 | B27: =IF(ISNUMBER(C27),C27,DATEVALUE(SUBSTITUTE(TRIM(C27),CHAR(160)," "))) -> 46238.582 | C27: 46238.582 | D27: Peter Alvarez | E27: =IF(TRIM(F27)="","Missing Email","Email Available") -> Email Available | F27: peter.alvarez465@yahoo.com | G27: Wireless Mouse | H27: Electronics | I27: ELC-MSE-WL | J27: 1 | K27: 11.99 | L27: VIP15 | M27: 1.8 | N27: 5.99 | O27: 16.18 | P27: PayPal | Q27: Online Store | R27: fulfilled | S27: United States | T27: Illinois | U27: =IF(AND(S27="United States",T27=""),"Missing state",IF(T27="","Not Required","Valid")) -> Valid | V27: New Jeffreystad
A28: #1963 | B28: =IF(ISNUMBER(C28),C28,DATEVALUE(SUBSTITUTE(TRIM(C28),CHAR(160)," "))) -> 46238 | C28: 04-08-2026 13:58 | D28: Sean Frank | E28: =IF(TRIM(F28)="","Missing Email","Email Available") -> Email Available | F28: sean.frank587@icloud.com | G28: Yoga Mat - Extra Thick | H28: Sports & Outdoors | I28: SP-YGM-EX | J28: 1 | K28: 22.99 | L28: VIP15 | M28: 3.45 | N28: 7.99 | O28: 27.53 | P28: Credit Card | Q28: Online Store | R28: fulfilled | S28: Australia | U28: =IF(AND(S28="United States",T28=""),"Missing state",IF(T28="","Not Required","Valid")) -> Not Required | V28: New Bruce
A29: #2040 | B29: =IF(ISNUMBER(C29),C29,DATEVALUE(SUBSTITUTE(TRIM(C29),CHAR(160)," "))) -> 46238.579 | C29: 46238.579 | D29: Sean Frank | E29: =IF(TRIM(F29)="","Missing Email","Email Available") -> Email Available | F29: sean.frank587@icloud.com | G29: Stainless Steel Water Bottle | H29: Home & Kitchen | I29: HK-BTL-750 | J29: 1 | K29: 12.99 | L29: VIP15 | M29: 1.95 | N29: 7.99 | O29: 19.03 | P29: PayPal | Q29: Facebook | R29: fulfilled | S29: Australia | U29: =IF(AND(S29="United States",T29=""),"Missing state",IF(T29="","Not Required","Valid")) -> Not Required | V29: Thompsonburgh
A30: #2130 | B30: =IF(ISNUMBER(C30),C30,DATEVALUE(SUBSTITUTE(TRIM(C30),CHAR(160)," "))) -> 46238.586 | C30: 46238.586 | D30: Jacqueline Graham | E30: =IF(TRIM(F30)="","Missing Email","Email Available") -> Email Available | F30: jacqueline.graham958@gmail.com | G30: Phone Case - Clear | H30: Electronics | I30: ELC-CSE-CLR | J30: 1 | K30: 8.99 | M30: 0 | N30: 5.99 | O30: 14.98 | P30: Shopify Payments | Q30: POS | R30: refunded | S30: Australia | U30: =IF(AND(S30="United States",T30=""),"Missing state",IF(T30="","Not Required","Valid")) -> Not Required | V30: West Jeffreystad
A31: #2204 | B31: =IF(ISNUMBER(C31),C31,DATEVALUE(SUBSTITUTE(TRIM(C31),CHAR(160)," "))) -> 46120 | C31: 08/04/2026 | D31: Maria Patterson | E31: =IF(TRIM(F31)="","Missing Email","Email Available") -> Email Available | F31: maria.patterson62@icloud.com | G31: Yoga Mat - Extra Thick | H31: Sports & Outdoors | I31: SP-YGM-EX | J31: 1 | K31: 22.99 | L31: VIP15 | M31: 3.45 | N31: 5.99 | O31: 25.53 | P31: Credit Card | Q31: Instagram | R31: cancelled | S31: United States | T31: Texas | U31: =IF(AND(S31="United States",T31=""),"Missing state",IF(T31="","Not Required","Valid")) -> Valid | V31: West Ericport
A32: #2212 | B32: =IF(ISNUMBER(C32),C32,DATEVALUE(SUBSTITUTE(TRIM(C32),CHAR(160)," "))) -> 46238.585 | C32: 46238.585 | D32: Anthony Patterson | E32: =IF(TRIM(F32)="","Missing Email","Email Available") -> Email Available | F32: anthony.patterson944@gmail.com | G32: Scented Soy Candle - Vanilla | H32: Home & Kitchen | I32: HK-CND-VAN | J32: 1 | K32: 9.99 | L32: BFCM25 | M32: 2.5 | N32: 4.99 | O32: 12.48 | P32: Shopify Payments | Q32: Instagram | R32: refunded | S32: Pakistan | U32: =IF(AND(S32="United States",T32=""),"Missing state",IF(T32="","Not Required","Valid")) -> Not Required | V32: Josephbury
A33: #2331 | B33: =IF(ISNUMBER(C33),C33,DATEVALUE(SUBSTITUTE(TRIM(C33),CHAR(160)," "))) -> 46238 | C33: 04-08-2026 13:55 | D33: Taylor Davis | E33: =IF(TRIM(F33)="","Missing Email","Email Available") -> Email Available | F33: taylor.davis403@outlook.com | G33: Scented Soy Candle - Vanilla | H33: Home & Kitchen | I33: HK-CND-VAN | J33: 2 | K33: $9.99 | L33: freeship | M33: 0 | N33: 0 | O33: 19.98 | P33: PayPal | Q33: Online Store | R33: fulfilled | S33: United States | T33: Florida | U33: =IF(AND(S33="United States",T33=""),"Missing state",IF(T33="","Not Required","Valid")) -> Valid | V33: East Rhonda
A34: #2402 | B34: =IF(ISNUMBER(C34),C34,DATEVALUE(SUBSTITUTE(TRIM(C34),CHAR(160)," "))) -> 46238.587 | C34: 46238.587 | D34: Dustin Mccoy | E34: =IF(TRIM(F34)="","Missing Email","Email Available") -> Email Available | F34: dustin.mccoy570@gmail.com | G34: Running Shoes - Men's | H34: Footwear | I34: FTW-RUN-M | J34: 1 | K34: 54.99 | M34: 0 | N34: 5.99 | O34: 60.98 | P34: PayPal | Q34: Online Store | R34: fulfilled | S34: Canada | U34: =IF(AND(S34="United States",T34=""),"Missing state",IF(T34="","Not Required","Valid")) -> Not Required | V34: Lake Mariatown
A35: #2415 | B35: =IF(ISNUMBER(C35),C35,DATEVALUE(SUBSTITUTE(TRIM(C35),CHAR(160)," "))) -> 46238.58 | C35: 46238.58 | D35: Vincent Rosales | E35: =IF(TRIM(F35)="","Missing Email","Email Available") -> Email Available | F35: vincent.rosales30@icloud.com | G35: Scented Soy Candle - Vanilla | H35: Home & Kitchen | I35: HK-CND-VAN | J35: 2 | K35: 9.99 | L35: FREESHIP | M35: 0 | N35: 0 | O35: 19.98 | P35: PayPal | Q35: Online Store | R35: pending | S35: United States | T35: Texas | U35: =IF(AND(S35="United States",T35=""),"Missing state",IF(T35="","Not Required","Valid")) -> Valid | V35: Stephaniebury
A36: #2436 | B36: =IF(ISNUMBER(C36),C36,DATEVALUE(SUBSTITUTE(TRIM(C36),CHAR(160)," "))) -> 46238.583 | C36: 46238.583 | D36: David Fleming | E36: =IF(TRIM(F36)="","Missing Email","Email Available") -> Email Available | F36: david.fleming778@gmail.com | G36: USB-C Fast Charger 20W | H36: Electronics | I36: ELC-CHG-20 | J36: 1 | K36: 15.49 | M36: 0 | N36: 4.99 | O36: 20.48 | P36: PayPal | Q36: Instagram | R36: fulfilled | S36: Australia | U36: =IF(AND(S36="United States",T36=""),"Missing state",IF(T36="","Not Required","Valid")) -> Not Required | V36: Port Dustin
A37: #2502 | B37: =IF(ISNUMBER(C37),C37,DATEVALUE(SUBSTITUTE(TRIM(C37),CHAR(160)," "))) -> 46238 | C37: 04-08-2026 13:57 | D37: Barbara Brown | E37: =IF(TRIM(F37)="","Missing Email","Email Available") -> Email Available | F37: barbara.brown26@gmail.com | G37: Slim Fit Denim Jeans | H37: Apparel | I37: JNS-BLU-32 | J37: 1 | K37: 39.99 | L37: VIP15 | M37: 6 | N37: 7.99 | O37: 41.98 | P37: Google Pay | Q37: Instagram | R37: refunded | S37: United States | T37: California | U37: =IF(AND(S37="United States",T37=""),"Missing state",IF(T37="","Not Required","Valid")) -> Valid | V37: North Benjamintown
A38: #2545 | B38: =IF(ISNUMBER(C38),C38,DATEVALUE(SUBSTITUTE(TRIM(C38),CHAR(160)," "))) -> 46238.587 | C38: 46238.587 | D38: Courtney Bullock | E38: =IF(TRIM(F38)="","Missing Email","Email Available") -> Email Available | F38: courtney.bullock860@outlook.com | G38: Ceramic Coffee Mug Set (4pc) | H38: Home & Kitchen | I38: HK-MUG-4PK | J38: 1 | K38: 18.99 | L38: FREESHIP | M38: 0 | N38: 0 | O38: 18.99 | P38: Google Pay | Q38: Instagram | R38: fulfilled | S38: United Kingdom | U38: =IF(AND(S38="United States",T38=""),"Missing state",IF(T38="","Not Required","Valid")) -> Not Required | V38: South Savannahton
A39: #2581 | B39: =IF(ISNUMBER(C39),C39,DATEVALUE(SUBSTITUTE(TRIM(C39),CHAR(160)," "))) -> 46238.586 | C39: 46238.586 | D39: Lindsay Shaw | E39: =IF(TRIM(F39)="","Missing Email","Email Available") -> Email Available | F39: lindsay.shaw178@icloud.com | G39: Leather Wallet - Brown | H39: Accessories | I39: ACC-WLT-BRN | J39: 1 | K39: 19.99 | M39: 0 | N39: 4.99 | O39: 24.98 | P39: Google Pay | Q39: Online Store | R39: refunded | S39: United Kingdom | U39: =IF(AND(S39="United States",T39=""),"Missing state",IF(T39="","Not Required","Valid")) -> Not Required | V39: Campbellmouth
A40: #2603 | B40: =IF(ISNUMBER(C40),C40,DATEVALUE(SUBSTITUTE(TRIM(C40),CHAR(160)," "))) -> 46120 | C40: 08/04/2026 | D40: Amanda Harris | E40: =IF(TRIM(F40)="","Missing Email","Email Available") -> Missing Email | G40: Polarized Sunglasses | H40: Accessories | I40: ACC-SUN-01 | J40: 1 | K40: 16.99 | M40: 0 | N40: 7.99 | O40: 24.98 | P40: Apple Pay | Q40: POS | R40: cancelled | S40: United States | T40: New York | U40: =IF(AND(S40="United States",T40=""),"Missing state",IF(T40="","Not Required","Valid")) -> Valid | V40: Lake Steven
A41: #2681 | B41: =DATE(VALUE(RIGHT(C41,4)),MATCH(LEFT(C41,3),{"Jan","Feb","Mar","Apr","May","Jun","Jul","Aug","Sep","Oct","Nov","Dec"},0),VALUE(MID(C41,5,2))) -> 46238 | C41: Aug 04, 2026 | D41: Farmer, Bradley | E41: =IF(TRIM(F41)="","Missing Email","Email Available") -> Email Available | F41: bradley.farmer290@icloud.com | G41: Running Shoes - Men's | H41: Footwear | I41: FTW-RUN-M | J41: 1 | K41: 54.99 | M41: 0 | N41: 7.99 | O41: 62.98 | P41: PayPal | Q41: Instagram | R41: fulfilled | S41: United Kingdom | U41: =IF(AND(S41="United States",T41=""),"Missing state",IF(T41="","Not Required","Valid")) -> Not Required | V41: Kimberlyview
A42: #2704 | B42: =IF(ISNUMBER(C42),C42,DATEVALUE(SUBSTITUTE(TRIM(C42),CHAR(160)," "))) -> 46120 | C42: 08/04/2026 | D42: Katie Coleman | E42: =IF(TRIM(F42)="","Missing Email","Email Available") -> Email Available | F42: katie.coleman262@outlook.com | G42: Classic Cotton T-Shirt | H42: Apparel | I42: TSH-BLK-M | J42: 1 | K42: 14.99 | L42: VIP15 | M42: 2.25 | N42: 5.99 | O42: 18.73 | P42: Google Pay | Q42: Online Store | R42: fulfilled | S42: Canada | U42: =IF(AND(S42="United States",T42=""),"Missing state",IF(T42="","Not Required","Valid")) -> Not Required | V42: East Annaville
A43: #2737 | B43: =IF(ISNUMBER(C43),C43,DATEVALUE(SUBSTITUTE(TRIM(C43),CHAR(160)," "))) -> 46238.588 | C43: 46238.588 | D43: Rose English | E43: =IF(TRIM(F43)="","Missing Email","Email Available") -> Email Available | F43: rose.english118@icloud.com | G43: Wireless Bluetooth Earbuds | H43: Electronics | I43: ELC-WBE-01 | J43: 1 | K43: 29.99 | M43: 0 | N43: 5.99 | O43: $35.98 | P43: Apple Pay | Q43: POS | R43: fulfilled | S43: Germany | U43: =IF(AND(S43="United States",T43=""),"Missing state",IF(T43="","Not Required","Valid")) -> Not Required | V43: East Courtneystad
A44: #2751 | B44: =IF(ISNUMBER(C44),C44,DATEVALUE(SUBSTITUTE(TRIM(C44),CHAR(160)," "))) -> 46238.584 | C44: 46238.584 | D44: Amanda Harris | E44: =IF(TRIM(F44)="","Missing Email","Email Available") -> Email Available | F44: amanda.harris197@gmail.com | G44: Vitamin C Serum 30ml | H44: Beauty | I44: BTY-SRM-30 | J44: 1 | K44: 24.99 | M44: 0 | N44: 4.99 | O44: 29.98 | P44: Credit Card | Q44: Facebook | R44: fulfilled | S44: United States | T44: AZ | U44: =IF(AND(S44="United States",T44=""),"Missing state",IF(T44="","Not Required","Valid")) -> Valid | V44: West Melissafurt
A45: #2792 | B45: =IF(ISNUMBER(C45),C45,DATEVALUE(SUBSTITUTE(TRIM(C45),CHAR(160)," "))) -> 46238.582 | C45: 46238.582 | D45: Donald Davis | E45: =IF(TRIM(F45)="","Missing Email","Email Available") -> Email Available | F45: donald.davis404@icloud.com | G45: Classic Cotton T-Shirt | H45: Apparel | I45: TSH-BLK-M | J45: 1 | K45: 14.99 | L45: BFCM25 | M45: 3.75 | N45: 7.99 | O45: 19.23 | P45: Shopify Payments | Q45: POS | R45: pending | S45: Canada | U45: =IF(AND(S45="United States",T45=""),"Missing state",IF(T45="","Not Required","Valid")) -> Not Required | V45: West Marcus
A46: #2850 | B46: =IF(ISNUMBER(C46),C46,DATEVALUE(SUBSTITUTE(TRIM(C46),CHAR(160)," "))) -> 46238 | C46: 2026-08-04 | D46: Houston, William | E46: =IF(TRIM(F46)="","Missing Email","Email Available") -> Email Available | F46: william.houston340@outlook.com | G46: Facial Cleanser 200ml | H46: Beauty | I46: BTY-CLN-200 | J46: 1 | K46: $13.49 | M46: 0 | N46: 5.99 | O46: 19.48 | P46: Apple Pay | Q46: Facebook | R46: fulfilled | S46: United States | T46: Ohio | U46: =IF(AND(S46="United States",T46=""),"Missing state",IF(T46="","Not Required","Valid")) -> Valid | V46: East Kimville
A47: #2893 | B47: =IF(ISNUMBER(C47),C47,DATEVALUE(SUBSTITUTE(TRIM(C47),CHAR(160)," "))) -> 46238.581 | C47: 46238.581 | D47: Darin Alvarez | E47: =IF(TRIM(F47)="","Missing Email","Email Available") -> Email Available | F47: darin.alvarez843@gmail.com | G47: Classic Cotton T-Shirt | H47: Apparel | I47: TSH-BLK-M | J47: 4 | K47: 14.99 | L47: SAVE20 | M47: 11.99 | N47: 7.99 | O47: 55.96 | P47: PayPal | Q47: Online Store | R47: cancelled | S47: Canada | U47: =IF(AND(S47="United States",T47=""),"Missing state",IF(T47="","Not Required","Valid")) -> Not Required | V47: Lake William
A48: #2917 | B48: =IF(ISNUMBER(C48),C48,DATEVALUE(SUBSTITUTE(TRIM(C48),CHAR(160)," "))) -> 46238.587 | C48: 46238.587 | D48: Andrew Cross | E48: =IF(TRIM(F48)="","Missing Email","Email Available") -> Email Available | F48: andrew.cross512@yahoo.com | G48: Scented Soy Candle - Vanilla | H48: Home & Kitchen | I48: HK-CND-VAN | J48: 2 | K48: 9.99 | L48: VIP15 | M48: 3 | N48: 7.99 | O48: 24.97 | P48: Google Pay | Q48: Online Store | R48: cancelled | S48: United States | T48: Arizona | U48: =IF(AND(S48="United States",T48=""),"Missing state",IF(T48="","Not Required","Valid")) -> Valid | V48: West Robert
A49: #2415 | B49: =IF(ISNUMBER(C49),C49,DATEVALUE(SUBSTITUTE(TRIM(C49),CHAR(160)," "))) -> 46238.58 | C49: 46238.58 | D49: Vincent Rosales | E49: =IF(TRIM(F49)="","Missing Email","Email Available") -> Email Available | F49: vincent.rosales30@icloud.com | G49: Scented Soy Candle - Vanilla | H49: Home & Kitchen | I49: HK-CND-VAN | J49: 2 | K49: $9.99 | L49: FREESHIP | M49: 0 | N49: 0 | O49: 19.98 | P49: PayPal | Q49: Online Store | R49: pending | S49: United States | T49: Texas | U49: =IF(AND(S49="United States",T49=""),"Missing state",IF(T49="","Not Required","Valid")) -> Valid | V49: Stephaniebury
A50: #2751 | B50: =IF(ISNUMBER(C50),C50,DATEVALUE(SUBSTITUTE(TRIM(C50),CHAR(160)," "))) -> 46238 | C50: 2026-08-04 | D50: Amanda Harris | E50: =IF(TRIM(F50)="","Missing Email","Email Available") -> Missing Email | G50: Vitamin C Serum 30ml | H50: Beauty | I50: BTY-SRM-30 | J50: 1 | K50: $24.99 | M50: 0 | N50: 4.99 | O50: 29.98 | P50: Credit Card | Q50: Facebook | R50: fulfilled | S50: United States | T50: Arizona | U50: =IF(AND(S50="United States",T50=""),"Missing state",IF(T50="","Not Required","Valid")) -> Valid | V50: West Melissafurt
A51: #1719 | B51: =IF(ISNUMBER(C51),C51,DATEVALUE(SUBSTITUTE(TRIM(C51),CHAR(160)," "))) -> 46120 | C51: 08/04/2026 | D51: Grace Ray | E51: =IF(TRIM(F51)="","Missing Email","Email Available") -> Email Available | F51: grace.ray807@yahoo.com | G51: Wireless Mouse | H51: Electronics | I51: ELC-MSE-WL | J51: 2 | K51: 11.99 | M51: 0 | N51: 7.99 | O51: 31.97 | P51: Apple Pay | Q51: Facebook | R51: cancelled | S51: United Kingdom | U51: =IF(AND(S51="United States",T51=""),"Missing state",IF(T51="","Not Required","Valid")) -> Not Required | V51: Lutzton
A52: #2204 | B52: =DATE(VALUE(RIGHT(C52,4)),MATCH(LEFT(C52,3),{"Jan","Feb","Mar","Apr","May","Jun","Jul","Aug","Sep","Oct","Nov","Dec"},0),VALUE(MID(C52,5,2))) -> 46238 | C52: Aug 04, 2026 | D52: Maria Patterson | E52: =IF(TRIM(F52)="","Missing Email","Email Available") -> Email Available | F52: maria.patterson62@icloud.com | G52: Yoga Mat - Extra Thick | H52: Sports & Outdoors | I52: SP-YGM-EX | J52: 1 | K52: 22.99 | L52: VIP15 | M52: 3.45 | N52: 5.99 | O52: 25.53 | P52: Credit Card | Q52: Instagram | R52: cancelled | S52: United States | T52: Texas | U52: =IF(AND(S52="United States",T52=""),"Missing state",IF(T52="","Not Required","Valid")) -> Valid | V52: West Ericport
A53: #1305 | B53: =IF(ISNUMBER(C53),C53,DATEVALUE(SUBSTITUTE(TRIM(C53),CHAR(160)," "))) -> 46238.586 | C53: 46238.586 | D53: Amy Maldonado | E53: =IF(TRIM(F53)="","Missing Email","Email Available") -> Email Available | F53: amy.maldonado44@gmail.com | G53: Polarized Sunglasses | H53: Accessories | I53: ACC-SUN-01 | J53: 1 | K53: 16.99 | M53: 0 | N53: 5.99 | O53: 22.98 | P53: PayPal | Q53: Online Store | R53: fulfilled | S53: Pakistan | U53: =IF(AND(S53="United States",T53=""),"Missing state",IF(T53="","Not Required","Valid")) -> Not Required | V53: Matthewstad
A54: #1781 | B54: =IF(ISNUMBER(C54),C54,DATEVALUE(SUBSTITUTE(TRIM(C54),CHAR(160)," "))) -> 46238.58 | C54: 46238.58 | D54: Sharon Brown | E54: =IF(TRIM(F54)="","Missing Email","Email Available") -> Email Available | F54: sharon.brown14@gmail.com | G54: Running Shoes - Men's | H54: Footwear | I54: FTW-RUN-M | J54: 1 | K54: 54.99 | M54: 0 | N54: 4.99 | O54: 59.98 | P54: Shopify Payments | Q54: POS | R54: fulfilled | S54: United States | T54: Arizona | U54: =IF(AND(S54="United States",T54=""),"Missing state",IF(T54="","Not Required","Valid")) -> Valid | V54: Clarkmouth
A55: #2130 | B55: =IF(ISNUMBER(C55),C55,DATEVALUE(SUBSTITUTE(TRIM(C55),CHAR(160)," "))) -> 46120 | C55: 08/04/2026 | D55: JACQUELINE GRAHAM | E55: =IF(TRIM(F55)="","Missing Email","Email Available") -> Email Available | F55: jacqueline.graham958@gmail.com | G55: Phone Case - Clear | H55: Electronics | I55: ELC-CSE-CLR | J55: 1 | K55: 8.99 | M55: 0 | N55: 5.99 | O55: 749 | P55: Shopify Payments | Q55: POS | R55: refunded | S55: Australia | U55: =IF(AND(S55="United States",T55=""),"Missing state",IF(T55="","Not Required","Valid")) -> Not Required | V55: West Jeffreystad
A56: #1866 | B56: =IF(ISNUMBER(C56),C56,DATEVALUE(SUBSTITUTE(TRIM(C56),CHAR(160)," "))) -> 46238.579 | C56: 46238.579 | D56: Melissa Jones | E56: =IF(TRIM(F56)="","Missing Email","Email Available") -> Email Available | F56: melissa.jones297@yahoo.com | G56: Ceramic Coffee Mug Set (4pc) | H56: Home & Kitchen | I56: HK-MUG-4PK | J56: 1 | K56: 18.99 | L56: FREESHIP | M56: 0 | N56: 0 | O56: 949.5 | P56: Credit Card | Q56: Online Store | R56: pending | S56: United States | T56: Florida | U56: =IF(AND(S56="United States",T56=""),"Missing state",IF(T56="","Not Required","Valid")) -> Valid | V56: Kelseybury
A57: #1859 | B57: =IF(ISNUMBER(C57),C57,DATEVALUE(SUBSTITUTE(TRIM(C57),CHAR(160)," "))) -> 46238.58 | C57: 46238.58 | D57: Sarah Webb | E57: =IF(TRIM(F57)="","Missing Email","Email Available") -> Email Available | F57: sarah.webb997@outlook.com | G57: Adjustable Dumbbell Set | H57: Sports & Outdoors | I57: SP-DMB-ADJ | J57: 3 | K57: 89.99 | L57: VIP15 | M57: 40.5 | N57: 0 | O57: 229.47 | P57: PayPal | Q57: Facebook | R57: fulfilled | S57: Germany | U57: =IF(AND(S57="United States",T57=""),"Missing state",IF(T57="","Not Required","Valid")) -> Not Required | V57: North Ronald
A58: #2545 | B58: =IF(ISNUMBER(C58),C58,DATEVALUE(SUBSTITUTE(TRIM(C58),CHAR(160)," "))) -> 46238.587 | C58: 46238.587 | D58: Courtney Bullock | E58: =IF(TRIM(F58)="","Missing Email","Email Available") -> Email Available | F58: courtney.bullock860@outlook.com | G58: Ceramic Coffee Mug Set (4pc) | H58: Home & Kitchen | I58: HK-MUG-4PK | J58: 1 | K58: 18.99 | L58: FREESHIP | M58: 0 | N58: 0 | O58: 18.99 | P58: Google Pay | Q58: Instagram | R58: fulfilled | S58: United Kingdom | U58: =IF(AND(S58="United States",T58=""),"Missing state",IF(T58="","Not Required","Valid")) -> Not Required | V58: South Savannahton
A59: #2917 | B59: =IF(ISNUMBER(C59),C59,DATEVALUE(SUBSTITUTE(TRIM(C59),CHAR(160)," "))) -> 46120 | C59: 08/04/2026 | D59: Andrew Cross | E59: =IF(TRIM(F59)="","Missing Email","Email Available") -> Email Available | F59: andrew.cross512@yahoo.com | G59: Scented Soy Candle - Vanilla | H59: Home & Kitchen | I59: HK-CND-VAN | J59: 2 | K59: 9.99 | L59: VIP15 | M59: 3 | N59: 7.99 | O59: 24.97 | P59: Google Pay | Q59: Online Store | R59: cancelled | S59: United States | T59: Arizona | U59: =IF(AND(S59="United States",T59=""),"Missing state",IF(T59="","Not Required","Valid")) -> Valid | V59: West Robert
A60: #1818 | B60: =IF(ISNUMBER(C60),C60,DATEVALUE(SUBSTITUTE(TRIM(C60),CHAR(160)," "))) -> 46238.583 | C60: 46238.583 | D60: Amanda Harris | E60: =IF(TRIM(F60)="","Missing Email","Email Available") -> Email Available | F60: amanda.harris197@gmail.com | G60: USB-C Fast Charger 20W | H60: Electronics | I60: ELC-CHG-20 | J60: 1 | K60: 15.49 | M60: 0 | N60: 5.99 | O60: $21.48 | P60: Google Pay | Q60: Instagram | R60: pending | S60: United States | T60: Washington | U60: =IF(AND(S60="United States",T60=""),"Missing state",IF(T60="","Not Required","Valid")) -> Valid | V60: Richardsonburgh
A61: #1948 | B61: =IF(ISNUMBER(C61),C61,DATEVALUE(SUBSTITUTE(TRIM(C61),CHAR(160)," "))) -> 46238.582 | C61: 46238.582 | D61: Peter Alvarez | E61: =IF(TRIM(F61)="","Missing Email","Email Available") -> Email Available | F61: peter.alvarez465@yahoo.com | G61: Wireless Mouse | H61: Electronics | I61: ELC-MSE-WL | J61: 1 | K61: $11.99 | L61: VIP15 | M61: 1.8 | N61: 5.99 | O61: 16.18 | P61: PayPal | Q61: Online Store | R61: fulfilled | S61: United States | T61: Illinois | U61: =IF(AND(S61="United States",T61=""),"Missing state",IF(T61="","Not Required","Valid")) -> Valid | V61: New Jeffreystad
A62: #2704 | B62: =IF(ISNUMBER(C62),C62,DATEVALUE(SUBSTITUTE(TRIM(C62),CHAR(160)," "))) -> 46238.588 | C62: 46238.588 | D62: Katie Coleman | E62: =IF(TRIM(F62)="","Missing Email","Email Available") -> Email Available | F62: katie.coleman262@outlook.com | G62: Classic Cotton T-Shirt | H62: Apparel | I62: TSH-BLK-M | J62: 1 | K62: 14.99 | L62: VIP15 | M62: 2.25 | N62: 5.99 | O62: 18.73 | P62: Google Pay | Q62: Online Store | R62: fulfilled | S62: Canada | U62: =IF(AND(S62="United States",T62=""),"Missing state",IF(T62="","Not Required","Valid")) -> Not Required | V62: East Annaville
A63: #2040 | B63: =IF(ISNUMBER(C63),C63,DATEVALUE(SUBSTITUTE(TRIM(C63),CHAR(160)," "))) -> 46238.579 | C63: 46238.579 | D63: Sean Frank | E63: =IF(TRIM(F63)="","Missing Email","Email Available") -> Email Available | F63: sean.frank587@icloud.com | G63: Stainless Steel Water Bottle | H63: Home & Kitchen | I63: HK-BTL-750 | J63: 1 | K63: 12.99 | L63: VIP15 | M63: 1.95 | N63: 7.99 | O63: 19.03 | P63: PayPal | Q63: Facebook | R63: fulfilled | S63: Australia | U63: =IF(AND(S63="United States",T63=""),"Missing state",IF(T63="","Not Required","Valid")) -> Not Required | V63: Thompsonburgh
A64: #2402 | B64: =IF(ISNUMBER(C64),C64,DATEVALUE(SUBSTITUTE(TRIM(C64),CHAR(160)," "))) -> 46238.587 | C64: 46238.587 | D64: Dustin Mccoy | E64: =IF(TRIM(F64)="","Missing Email","Email Available") -> Email Available | F64: dustin.mccoy570@gmail.com | G64: Running Shoes - Men's | H64: Footwear | I64: FTW-RUN-M | J64: 1 | K64: 54.99 | M64: 0 | N64: 5.99 | O64: 60.98 | P64: PayPal | Q64: Online Store | R64: fulfilled | S64: Canada | U64: =IF(AND(S64="United States",T64=""),"Missing state",IF(T64="","Not Required","Valid")) -> Not Required | V64: Lake Mariatown
A65: #2681 | B65: =IF(ISNUMBER(C65),C65,DATEVALUE(SUBSTITUTE(TRIM(C65),CHAR(160)," "))) -> 46238.583 | C65: 46238.583 | D65: Bradley Farmer | E65: =IF(TRIM(F65)="","Missing Email","Email Available") -> Email Available | F65: bradley.farmer290@icloud.com | G65: Running Shoes - Men's | H65: Footwear | I65: FTW-RUN-M | J65: 1 | K65: 54.99 | M65: 0 | N65: 7.99 | O65: 62.98 | P65: PayPal | Q65: Instagram | R65: fulfilled | S65: United Kingdom | U65: =IF(AND(S65="United States",T65=""),"Missing state",IF(T65="","Not Required","Valid")) -> Not Required | V65: Kimberlyview
A66: #2502 | B66: =IF(ISNUMBER(C66),C66,DATEVALUE(SUBSTITUTE(TRIM(C66),CHAR(160)," "))) -> 46238.582 | C66: 46238.582 | D66: Barbara Brown | E66: =IF(TRIM(F66)="","Missing Email","Email Available") -> Email Available | F66: barbara.brown26@gmail.com | G66: Slim Fit Denim Jeans | H66: Apparel | I66: JNS-BLU-32 | J66: 1 | K66: 39.99 | L66: VIP15 | M66: 6 | N66: 7.99 | O66: 41.98 | P66: Google Pay | Q66: Instagram | R66: refunded | S66: United States | T66: California | U66: =IF(AND(S66="United States",T66=""),"Missing state",IF(T66="","Not Required","Valid")) -> Valid | V66: North Benjamintown
A67: #2436 | B67: =IF(ISNUMBER(C67),C67,DATEVALUE(SUBSTITUTE(TRIM(C67),CHAR(160)," "))) -> 46238.583 | C67: 46238.583 | D67: David Fleming | E67: =IF(TRIM(F67)="","Missing Email","Email Available") -> Email Available | F67: david.fleming778@gmail.com | G67: USB-C Fast Charger 20W | H67: Electronics | I67: ELC-CHG-20 | J67: 1 | K67: 15.49 | M67: 0 | N67: 4.99 | O67: 20.48 | P67: PayPal | Q67: Instagram | R67: fulfilled | S67: Australia | U67: =IF(AND(S67="United States",T67=""),"Missing state",IF(T67="","Not Required","Valid")) -> Not Required | V67: Port Dustin
A68: #1262 | B68: =IF(ISNUMBER(C68),C68,DATEVALUE(SUBSTITUTE(TRIM(C68),CHAR(160)," "))) -> 46238.586 | C68: 46238.586 | D68: Mark Mata | E68: =IF(TRIM(F68)="","Missing Email","Email Available") -> Email Available | F68: mark.mata757@outlook.com | G68: Facial Cleanser 200ml | H68: Beauty | I68: BTY-CLN-200 | J68: 1 | K68: 13.49 | M68: $0.00 | N68: 7.99 | O68: 21.48 | P68: Apple Pay | Q68: Facebook | R68: pending | S68: United States | T68: Washington | U68: =IF(AND(S68="United States",T68=""),"Missing state",IF(T68="","Not Required","Valid")) -> Valid | V68: Davidburgh
A69: #2792 | B69: =IF(ISNUMBER(C69),C69,DATEVALUE(SUBSTITUTE(TRIM(C69),CHAR(160)," "))) -> 46120 | C69: 08/04/2026 | D69: Donald Davis | E69: =IF(TRIM(F69)="","Missing Email","Email Available") -> Email Available | F69: donald.davis404@icloud.com | G69: Classic Cotton T-Shirt | H69: Apparel | I69: TSH-BLK-M | J69: 1 | K69: 14.99 | L69: BFCM25 | M69: 3.75 | N69: 7.99 | O69: 19.23 | P69: Shopify Payments | Q69: POS | R69: pending | S69: Canada | U69: =IF(AND(S69="United States",T69=""),"Missing state",IF(T69="","Not Required","Valid")) -> Not Required | V69: West Marcus
A70: #2893 | B70: =IF(ISNUMBER(C70),C70,DATEVALUE(SUBSTITUTE(TRIM(C70),CHAR(160)," "))) -> 46238.581 | C70: 46238.581 | D70: Darin Alvarez | E70: =IF(TRIM(F70)="","Missing Email","Email Available") -> Email Available | F70: darin.alvarez843@gmail.com | G70: Classic Cotton T-Shirt | H70: Apparel | I70: TSH-BLK-M | J70: 4 | K70: 14.99 | L70: SAVE20 | M70: 11.99 | N70: 7.99 | O70: 55.96 | P70: PayPal | Q70: Online Store | R70: cancelled | S70: Canada | U70: =IF(AND(S70="United States",T70=""),"Missing state",IF(T70="","Not Required","Valid")) -> Not Required | V70: Lake William
A71: #1027 | B71: =IF(ISNUMBER(C71),C71,DATEVALUE(SUBSTITUTE(TRIM(C71),CHAR(160)," "))) -> 46238.583 | C71: 46238.583 | D71: Sandra Wilson | E71: =IF(TRIM(F71)="","Missing Email","Email Available") -> Missing Email | G71: Vitamin C Serum 30ml | H71: Beauty | I71: BTY-SRM-30 | J71: 1 | K71: 24.99 | L71: VIP15 | M71: 3.75 | N71: 7.99 | O71: 29.23 | P71: Apple Pay | Q71: Online Store | R71: pending | S71: Canada | U71: =IF(AND(S71="United States",T71=""),"Missing state",IF(T71="","Not Required","Valid")) -> Not Required | V71: Hollyport
A72: #2581 | B72: =IF(ISNUMBER(C72),C72,DATEVALUE(SUBSTITUTE(TRIM(C72),CHAR(160)," "))) -> 46238.586 | C72: 46238.586 | D72: Lindsay Shaw | E72: =IF(TRIM(F72)="","Missing Email","Email Available") -> Email Available | F72: lindsay.shaw178@icloud.com | G72: Leather Wallet - Brown | H72: Accessories | I72: ACC-WLT-BRN | J72: 1 | K72: 19.99 | M72: 0 | N72: 4.99 | O72: 24.98 | P72: Google Pay | Q72: Online Store | R72: refunded | S72: United Kingdom | U72: =IF(AND(S72="United States",T72=""),"Missing state",IF(T72="","Not Required","Valid")) -> Not Required | V72: Campbellmouth
A73: #1652 | B73: =IF(ISNUMBER(C73),C73,DATEVALUE(SUBSTITUTE(TRIM(C73),CHAR(160)," "))) -> 46238.585 | C73: 46238.585 | D73: Sean Frank | E73: =IF(TRIM(F73)="","Missing Email","Email Available") -> Email Available | F73: sean.frank587@icloud.com | G73: Kids Building Blocks Set | H73: Toys | I73: TOY-BLK-SET | J73: 2 | K73: 27.99 | L73: WELCOME10 | M73: 5.6 | N73: 7.99 | O73: 58.37 | P73: Credit Card | Q73: Facebook | R73: fulfilled | S73: Australia | U73: =IF(AND(S73="United States",T73=""),"Missing state",IF(T73="","Not Required","Valid")) -> Not Required | V73: Port Josephborough
A74: #2603 | B74: =IF(ISNUMBER(C74),C74,DATEVALUE(SUBSTITUTE(TRIM(C74),CHAR(160)," "))) -> 46238.585 | C74: 46238.585 | D74: Amanda Harris | E74: =IF(TRIM(F74)="","Missing Email","Email Available") -> Email Available | F74: amanda.harris197@gmail.com | G74: Polarized Sunglasses | H74: Accessories | I74: ACC-SUN-01 | J74: 1 | K74: 16.99 | M74: 0 | N74: 7.99 | O74: 24.98 | P74: Apple Pay | Q74: POS | R74: cancelled | S74: United States | T74: NY | U74: =IF(AND(S74="United States",T74=""),"Missing state",IF(T74="","Not Required","Valid")) -> Valid | V74: Lake Steven
A75: #2850 | B75: =DATE(VALUE(RIGHT(C75,4)),MATCH(LEFT(C75,3),{"Jan","Feb","Mar","Apr","May","Jun","Jul","Aug","Sep","Oct","Nov","Dec"},0),VALUE(MID(C75,5,2))) -> 46238 | C75: Aug 04, 2026 | D75: William Houston | E75: =IF(TRIM(F75)="","Missing Email","Email Available") -> Missing Email | G75: Facial Cleanser 200ml | H75: Beauty | I75: BTY-CLN-200 | J75: 1 | K75: 13.49 | M75: 0 | N75: 5.99 | O75: 19.48 | P75: Apple Pay | Q75: Facebook | R75: fulfilled | S75: United States | T75: OH | U75: =IF(AND(S75="United States",T75=""),"Missing state",IF(T75="","Not Required","Valid")) -> Valid | V75: East Kimville
A76: #2212 | B76: =IF(ISNUMBER(C76),C76,DATEVALUE(SUBSTITUTE(TRIM(C76),CHAR(160)," "))) -> 46238.585 | C76: 46238.585 | D76: Patterson, Anthony | E76: =IF(TRIM(F76)="","Missing Email","Email Available") -> Email Available | F76: anthony.patterson944@gmail.com | G76: Scented Soy Candle - Vanilla | H76: Home & Kitchen | I76: HK-CND-VAN | J76: 1 | K76: 9.99 | L76: BFCM25 | M76: 2.5 | N76: 4.99 | O76: 12.48 | P76: Shopify Payments | Q76: Instagram | R76: refunded | S76: Pakistan | U76: =IF(AND(S76="United States",T76=""),"Missing state",IF(T76="","Not Required","Valid")) -> Not Required | V76: Josephbury
A77: #1003 | B77: =DATE(VALUE(RIGHT(C77,4)),MATCH(LEFT(C77,3),{"Jan","Feb","Mar","Apr","May","Jun","Jul","Aug","Sep","Oct","Nov","Dec"},0),VALUE(MID(C77,5,2))) -> 46238 | C77: Aug 04, 2026 | D77: Thomas Rojas | E77: =IF(TRIM(F77)="","Missing Email","Email Available") -> Email Available | F77: thomas.rojas667@icloud.com | G77: Slim Fit Denim Jeans | H77: Apparel | I77: JNS-BLU-32 | J77: 1 | K77: 39.99 | M77: 0 | N77: 5.99 | O77: 45.98 | P77: Credit Card | Q77: Online Store | R77: fulfilled | S77: United States | T77: North Carolina | U77: =IF(AND(S77="United States",T77=""),"Missing state",IF(T77="","Not Required","Valid")) -> Valid | V77: West Cynthialand
A78: #2331 | B78: =IF(ISNUMBER(C78),C78,DATEVALUE(SUBSTITUTE(TRIM(C78),CHAR(160)," "))) -> 46238.58 | C78: 46238.58 | D78: Taylor Davis | E78: =IF(TRIM(F78)="","Missing Email","Email Available") -> Email Available | F78: taylor.davis403@outlook.com | G78: Scented Soy Candle - Vanilla | H78: Home & Kitchen | I78: HK-CND-VAN | J78: 2 | K78: 9.99 | L78: FREESHIP | M78: 0 | N78: 0 | O78: 19.98 | P78: PayPal | Q78: Online Store | R78: fulfilled | S78: United States | T78: Florida | U78: =IF(AND(S78="United States",T78=""),"Missing state",IF(T78="","Not Required","Valid")) -> Valid | V78: East Rhonda
A79: #1172 | B79: =IF(ISNUMBER(C79),C79,DATEVALUE(SUBSTITUTE(TRIM(C79),CHAR(160)," "))) -> 46238.584 | C79: 46238.584 | D79: Tina Singh | E79: =IF(TRIM(F79)="","Missing Email","Email Available") -> Email Available | F79: tina.singh98@icloud.com | G79: Leather Wallet - Brown | H79: Accessories | I79: ACC-WLT-BRN | J79: 1 | K79: 19.99 | M79: 0 | N79: 5.99 | O79: 25.98 | P79: Credit Card | Q79: Online Store | R79: fulfilled | S79: United States | T79: Washington | U79: =IF(AND(S79="United States",T79=""),"Missing state",IF(T79="","Not Required","Valid")) -> Valid | V79: East Heathertown
A80: #2737 | B80: =IF(ISNUMBER(C80),C80,DATEVALUE(SUBSTITUTE(TRIM(C80),CHAR(160)," "))) -> 46238.588 | C80: 46238.588 | D80: Rose English | E80: =IF(TRIM(F80)="","Missing Email","Email Available") -> Email Available | F80: rose.english118@icloud.com | G80: Wireless Bluetooth Earbuds | H80: Electronics | I80: ELC-WBE-01 | J80: 1 | K80: $29.99 | M80: 0 | N80: 5.99 | O80: 35.98 | P80: Apple Pay | Q80: POS | R80: fulfilled | S80: Germany | U80: =IF(AND(S80="United States",T80=""),"Missing state",IF(T80="","Not Required","Valid")) -> Not Required | V80: East Courtneystad
A81: #1798 | B81: =IF(ISNUMBER(C81),C81,DATEVALUE(SUBSTITUTE(TRIM(C81),CHAR(160)," "))) -> 46120 | C81: 08/04/2026 | D81: Tina Singh | E81: =IF(TRIM(F81)="","Missing Email","Email Available") -> Missing Email | G81: Adjustable Dumbbell Set | H81: Sports & Outdoors | I81: SP-DMB-ADJ | J81: 2 | K81: 89.99 | M81: 0 | N81: 0 | O81: 179.98 | P81: Google Pay | Q81: POS | R81: pending | S81: United States | T81: Georgia | U81: =IF(AND(S81="United States",T81=""),"Missing state",IF(T81="","Not Required","Valid")) -> Valid | V81: North Shannon
A82: #1963 | B82: =IF(ISNUMBER(C82),C82,DATEVALUE(SUBSTITUTE(TRIM(C82),CHAR(160)," "))) -> 46238.582 | C82: 46238.582 | D82: Sean Frank | E82: =IF(TRIM(F82)="","Missing Email","Email Available") -> Email Available | F82: sean.frank587@icloud.com | G82: Yoga Mat - Extra Thick | H82: Sports & Outdoors | I82: SP-YGM-EX | J82: 1 | K82: 22.99 | L82: VIP15 | M82: 3.45 | N82: 7.99 | O82: 27.53 | P82: Credit Card | Q82: Online Store | R82: fulfilled | S82: Australia | U82: =IF(AND(S82="United States",T82=""),"Missing state",IF(T82="","Not Required","Valid")) -> Not Required | V82: New Bruce
A83: #1260 | B83: =IF(ISNUMBER(C83),C83,DATEVALUE(SUBSTITUTE(TRIM(C83),CHAR(160)," "))) -> 46238.586 | C83: 46238.586 | D83: Morgan Brown | E83: =IF(TRIM(F83)="","Missing Email","Email Available") -> Email Available | F83: morgan.brown933@gmail.com | G83: Wireless Bluetooth Earbuds | H83: Electronics | I83: ELC-WBE-01 | J83: 1 | K83: 29.99 | L83: FREESHIP | M83: 0 | N83: 0 | O83: 29.99 | P83: Apple Pay | Q83: Online Store | R83: pending | S83: United States | T83: Florida | U83: =IF(AND(S83="United States",T83=""),"Missing state",IF(T83="","Not Required","Valid")) -> Valid | V83: Austinbury
A84: #1001 | B84: =IF(ISNUMBER(C84),C84,DATEVALUE(SUBSTITUTE(TRIM(C84),CHAR(160)," "))) -> 46238.581 | C84: 46238.581 | D84: Glenn Mcmahon | E84: =IF(TRIM(F84)="","Missing Email","Email Available") -> Email Available | F84: glenn.mcmahon733@yahoo.com | G84: Stainless Steel Water Bottle | H84: Home & Kitchen | I84: HK-BTL-750 | J84: 1 | K84: 12.99 | L84: SAVE20 | M84: $2.60 | N84: 5.99 | O84: 16.38 | P84: Google Pay | Q84: Online Store | R84: pending | S84: United States | T84: Georgia | U84: =IF(AND(S84="United States",T84=""),"Missing state",IF(T84="","Not Required","Valid")) -> Valid | V84: Jamesfurt
A85: #1002 | B85: =IF(ISNUMBER(C85),C85,DATEVALUE(SUBSTITUTE(TRIM(C85),CHAR(160)," "))) -> 46238.583 | C85: 46238.583 | D85: Miranda Gray | E85: =IF(TRIM(F85)="","Missing Email","Email Available") -> Email Available | F85: miranda.gray649@yahoo.com | G85: Portable Power Bank 10000mAh | H85: Electronics | I85: ELC-PWB-10K | J85: 1 | K85: 21.99 | L85: FREESHIP | M85: 0 | N85: 0 | O85: 21.99 | P85: Shopify Payments | Q85: Facebook | R85: refunded | S85: Pakistan | U85: =IF(AND(S85="United States",T85=""),"Missing state",IF(T85="","Not Required","Valid")) -> Not Required | V85: Port Davidshire
A86: #1004 | B86: =IF(ISNUMBER(C86),C86,DATEVALUE(SUBSTITUTE(TRIM(C86),CHAR(160)," "))) -> 46238.588 | C86: 46238.588 | D86: Robyn Hughes | E86: =IF(TRIM(F86)="","Missing Email","Email Available") -> Email Available | F86: robyn.hughes771@gmail.com | G86: Scented Soy Candle - Vanilla | H86: Home & Kitchen | I86: HK-CND-VAN | J86: 1 | K86: 9.99 | L86: FREESHIP | M86: 0 | N86: 0 | O86: 9.99 | P86: Google Pay | Q86: Facebook | R86: fulfilled | S86: United States | T86: New York | U86: =IF(AND(S86="United States",T86=""),"Missing state",IF(T86="","Not Required","Valid")) -> Valid | V86: New Debra
A87: #1005 | B87: =IF(ISNUMBER(C87),C87,DATEVALUE(SUBSTITUTE(TRIM(C87),CHAR(160)," "))) -> 46238.579 | C87: 46238.579 | D87: Sharon Brown | E87: =IF(TRIM(F87)="","Missing Email","Email Available") -> Email Available | F87: sharon.brown14@gmail.com | G87: Classic Cotton T-Shirt | H87: Apparel | I87: TSH-BLK-L | J87: 1 | K87: 14.99 | L87: WELCOME10 | M87: 1.5 | N87: 5.99 | O87: 19.48 | P87: Apple Pay | Q87: Online Store | R87: fulfilled | S87: United States | T87: Illinois | U87: =IF(AND(S87="United States",T87=""),"Missing state",IF(T87="","Not Required","Valid")) -> Valid | V87: Lake Angel
A88: #1006 | B88: =IF(ISNUMBER(C88),C88,DATEVALUE(SUBSTITUTE(TRIM(C88),CHAR(160)," "))) -> 46238.584 | C88: 46238.584 | D88: Joshua Anderson | E88: =IF(TRIM(F88)="","Missing Email","Email Available") -> Email Available | F88: joshua.anderson662@gmail.com | G88: Scented Soy Candle - Vanilla | H88: Home & Kitchen | I88: HK-CND-VAN | J88: 2 | K88: 9.99 | L88: WELCOME10 | M88: 2 | N88: 4.99 | O88: 22.97 | P88: PayPal | Q88: Facebook | R88: fulfilled | S88: Canada | U88: =IF(AND(S88="United States",T88=""),"Missing state",IF(T88="","Not Required","Valid")) -> Not Required | V88: Joshuastad
A89: #1007 | B89: =IF(ISNUMBER(C89),C89,DATEVALUE(SUBSTITUTE(TRIM(C89),CHAR(160)," "))) -> 46238.587 | C89: 46238.587 | D89: Maria Leon | E89: =IF(TRIM(F89)="","Missing Email","Email Available") -> Email Available | F89: maria.leon163@outlook.com | G89: Adjustable Dumbbell Set | H89: Sports & Outdoors | I89: SP-DMB-ADJ | J89: 1 | K89: 89.99 | M89: 0 | N89: 0 | O89: 89.99 | P89: Apple Pay | Q89: Online Store | R89: refunded | S89: Canada | U89: =IF(AND(S89="United States",T89=""),"Missing state",IF(T89="","Not Required","Valid")) -> Not Required | V89: North Rebeccaland
A90: #1008 | B90: =IF(ISNUMBER(C90),C90,DATEVALUE(SUBSTITUTE(TRIM(C90),CHAR(160)," "))) -> 46238.58 | C90: 46238.58 | D90: austin norris | E90: =IF(TRIM(F90)="","Missing Email","Email Available") -> Email Available | F90: austin.norris15@gmail.com | G90: Running Shoes - Women's | H90: Footwear | I90: FTW-RUN-W | J90: 1 | K90: 54.99 | M90: 0 | N90: 4.99 | O90: 59.98 | P90: Credit Card | Q90: Instagram | R90: fulfilled | S90: United States | T90: Florida | U90: =IF(AND(S90="United States",T90=""),"Missing state",IF(T90="","Not Required","Valid")) -> Valid | V90: South Kaitlyn
A91: #1009 | B91: =IF(ISNUMBER(C91),C91,DATEVALUE(SUBSTITUTE(TRIM(C91),CHAR(160)," "))) -> 46238.588 | C91: 46238.588 | D91: Jennifer Burke | E91: =IF(TRIM(F91)="","Missing Email","Email Available") -> Email Available | F91: jennifer.burke472@icloud.com | G91: Running Shoes - Women's | H91: Footwear | I91: FTW-RUN-W | J91: 3 | K91: 54.99 | L91: save20 | M91: 32.99 | N91: 0 | O91: $131.98 | P91: Google Pay | Q91: Online Store | R91: cancelled | S91: Pakistan | U91: =IF(AND(S91="United States",T91=""),"Missing state",IF(T91="","Not Required","Valid")) -> Not Required | V91: Reneemouth
A92: #1010 | B92: =IF(ISNUMBER(C92),C92,DATEVALUE(SUBSTITUTE(TRIM(C92),CHAR(160)," "))) -> 46238 | C92: 04-08-2026 14:06 | D92: Robert Miller | E92: =IF(TRIM(F92)="","Missing Email","Email Available") -> Email Available | F92: robert.miller69@yahoo.com | G92: Leather Wallet - Brown | H92: Accessories | I92: ACC-WLT-BRN | J92: 1 | K92: 19.99 | L92: WELCOME10 | M92: 2 | N92: 4.99 | O92: 22.98 | P92: PayPal | Q92: Online Store | R92: refunded | S92: Australia | U92: =IF(AND(S92="United States",T92=""),"Missing state",IF(T92="","Not Required","Valid")) -> Not Required | V92: Ortizview
A93: #1011 | B93: =IF(ISNUMBER(C93),C93,DATEVALUE(SUBSTITUTE(TRIM(C93),CHAR(160)," "))) -> 46238.585 | C93: 46238.585 | D93: Patricia Townsend | E93: =IF(TRIM(F93)="","Missing Email","Email Available") -> Missing Email | G93: Yoga Mat - Extra Thick | H93: Sports & Outdoors | I93: SP-YGM-EX | J93: 1 | K93: 22.99 | M93: 0 | N93: 7.99 | O93: 30.98 | P93: Shopify Payments | Q93: POS | R93: fulfilled | S93: United States | T93: Ohio | U93: =IF(AND(S93="United States",T93=""),"Missing state",IF(T93="","Not Required","Valid")) -> Valid | V93: West Stephentown
A94: #1012 | B94: =IF(ISNUMBER(C94),C94,DATEVALUE(SUBSTITUTE(TRIM(C94),CHAR(160)," "))) -> 46238.58 | C94: 46238.58 | D94: Karen Jones | E94: =IF(TRIM(F94)="","Missing Email","Email Available") -> Email Available | F94: karen.jones287@icloud.com | G94: Stainless Steel Water Bottle | H94: Home & Kitchen | I94: HK-BTL-750 | J94: 1 | K94: 12.99 | L94: BFCM25 | M94: 3.25 | N94: 4.99 | O94: $14.73 | P94: Shopify Payments | Q94: Online Store | R94: refunded | S94: Australia | U94: =IF(AND(S94="United States",T94=""),"Missing state",IF(T94="","Not Required","Valid")) -> Not Required | V94: South Joseph
A95: #1013 | B95: =IF(ISNUMBER(C95),C95,DATEVALUE(SUBSTITUTE(TRIM(C95),CHAR(160)," "))) -> 46238.585 | C95: 46238.585 | D95: Anthony Patterson | E95: =IF(TRIM(F95)="","Missing Email","Email Available") -> Email Available | F95: anthony.patterson944@gmail.com | G95: Resistance Bands Set | H95: Sports & Outdoors | I95: SP-RBS-SET | J95: 1 | K95: 13.99 | L95: save20 | M95: 2.8 | N95: 5.99 | O95: 17.18 | P95: Apple Pay | Q95: Instagram | R95: cancelled | S95: Pakistan | U95: =IF(AND(S95="United States",T95=""),"Missing state",IF(T95="","Not Required","Valid")) -> Not Required | V95: West Denisemouth
A96: #1014 | B96: =IF(ISNUMBER(C96),C96,DATEVALUE(SUBSTITUTE(TRIM(C96),CHAR(160)," "))) -> 46238.585 | C96: 46238.585 | D96: Frederick Bean | E96: =IF(TRIM(F96)="","Missing Email","Email Available") -> Email Available | F96: frederick.bean141@outlook.com | G96: Polarized Sunglasses | H96: Accessories | I96: ACC-SUN-01 | J96: 1 | K96: 16.99 | M96: 0 | N96: 5.99 | O96: 22.98 | P96: Credit Card | Q96: Online Store | R96: fulfilled | S96: United States | T96: Florida | U96: =IF(AND(S96="United States",T96=""),"Missing state",IF(T96="","Not Required","Valid")) -> Valid | V96: Kimberlychester
A97: #1015 | B97: =IF(ISNUMBER(C97),C97,DATEVALUE(SUBSTITUTE(TRIM(C97),CHAR(160)," "))) -> 46238.589 | C97: 46238.589 | D97: Linda Byrd | E97: =IF(TRIM(F97)="","Missing Email","Email Available") -> Email Available | F97: linda.byrd87@outlook.com | G97: Yoga Mat - Extra Thick | H97: Sports & Outdoors | I97: SP-YGM-EX | J97: 1 | K97: 22.99 | L97: SAVE20 | M97: 4.6 | N97: 4.99 | O97: 23.38 | P97: Google Pay | Q97: POS | R97: fulfilled | S97: United States | T97: AZ | U97: =IF(AND(S97="United States",T97=""),"Missing state",IF(T97="","Not Required","Valid")) -> Valid | V97: Deanstad
A98: #1016 | B98: =IF(ISNUMBER(C98),C98,DATEVALUE(SUBSTITUTE(TRIM(C98),CHAR(160)," "))) -> 46120 | C98: 08/04/2026 | D98: Rachel Jimenez | E98: =IF(TRIM(F98)="","Missing Email","Email Available") -> Email Available | F98: rachel.jimenez326@outlook.com | G98: Adjustable Dumbbell Set | H98: Sports & Outdoors | I98: SP-DMB-ADJ | J98: 1 | K98: 89.99 | M98: 0 | N98: 0 | O98: 89.99 | P98: Google Pay | Q98: POS | R98: fulfilled | S98: United States | T98: Texas | U98: =IF(AND(S98="United States",T98=""),"Missing state",IF(T98="","Not Required","Valid")) -> Valid | V98: Larsonchester
A99: #1017 | B99: =IF(ISNUMBER(C99),C99,DATEVALUE(SUBSTITUTE(TRIM(C99),CHAR(160)," "))) -> 46238 | C99: 2026-08-04 | D99: John Jacobs | E99: =IF(TRIM(F99)="","Missing Email","Email Available") -> Email Available | F99: john.jacobs137@yahoo.com | G99: Hooded Sweatshirt | H99: Apparel | I99: APR-HOD-GRY | J99: 2 | K99: 34.99 | M99: 0 | N99: 4.99 | O99: 74.97 | P99: Shopify Payments | Q99: Online Store | R99: fulfilled | S99: Australia | U99: =IF(AND(S99="United States",T99=""),"Missing state",IF(T99="","Not Required","Valid")) -> Not Required | V99: South Beverlyton
A100: #1018 | B100: =IF(ISNUMBER(C100),C100,DATEVALUE(SUBSTITUTE(TRIM(C100),CHAR(160)," "))) -> 46238 | C100: 2026-08-04 | D100: Mary Phillips | E100: =IF(TRIM(F100)="","Missing Email","Email Available") -> Email Available | F100: mary.phillips944@yahoo.com | G100: Wireless Bluetooth Earbuds | H100: Electronics | I100: ELC-WBE-01 | J100: 1 | K100: 29.99 | M100: 0 | N100: 7.99 | O100: 37.98 | P100: PayPal | Q100: POS | R100: fulfilled | S100: United States | T100: AZ | U100: =IF(AND(S100="United States",T100=""),"Missing state",IF(T100="","Not Required","Valid")) -> Valid | V100: Guerraton
...
